README.md
setup.py
EARL_pytorch.egg-info/PKG-INFO
EARL_pytorch.egg-info/SOURCES.txt
EARL_pytorch.egg-info/dependency_links.txt
EARL_pytorch.egg-info/requires.txt
EARL_pytorch.egg-info/top_level.txt
earl_pytorch/__init__.py
earl_pytorch/dataset/__init__.py
earl_pytorch/dataset/create_dataset.py
earl_pytorch/dataset/create_dataset_v2.py
earl_pytorch/dataset/create_dataset_v3.py
earl_pytorch/dataset/dataset.py
earl_pytorch/model/__init__.py
earl_pytorch/model/earl.py
earl_pytorch/model/earl_perceiver.py
earl_pytorch/model/eprl.py
earl_pytorch/model/outputs.py
earl_pytorch/util/__init__.py
earl_pytorch/util/analyze.py
earl_pytorch/util/constants.py
earl_pytorch/util/util.py
rlgym_tools/__init__.py
rlgym_tools/better_gym.py
rlgym_tools/filtered_env.py
rlgym_tools/replay_converter.py
rlgym_tools/version.py
rlgym_tools/autonomous_utils/__init__.py
rlgym_tools/autonomous_utils/agent.py
rlgym_tools/autonomous_utils/autonomous_env.py
rlgym_tools/autonomous_utils/model.py
rlgym_tools/autonomous_utils/preset.py
rlgym_tools/autonomous_utils/test.py
rlgym_tools/examples/__init__.py
rlgym_tools/examples/action_test.py
rlgym_tools/examples/rllib_example.py
rlgym_tools/examples/sb3_multi_example.py
rlgym_tools/examples/sb3_multiple_models_example.py
rlgym_tools/extra_action_parsers/__init__.py
rlgym_tools/extra_action_parsers/kbm_act.py
rlgym_tools/extra_action_parsers/lookup_act.py
rlgym_tools/extra_obs/__init__.py
rlgym_tools/extra_obs/advanced_padder.py
rlgym_tools/extra_obs/advanced_stacker.py
rlgym_tools/extra_obs/general_stacking.py
rlgym_tools/extra_rewards/__init__.py
rlgym_tools/extra_rewards/anneal_rewards.py
rlgym_tools/extra_rewards/diff_reward.py
rlgym_tools/extra_rewards/distribute_rewards.py
rlgym_tools/extra_rewards/jump_touch_reward.py
rlgym_tools/extra_rewards/kickoff_reward.py
rlgym_tools/extra_rewards/multi_model_rewards.py
rlgym_tools/extra_rewards/multiply_rewards.py
rlgym_tools/extra_rewards/sequential_rewards.py
rlgym_tools/extra_state_setters/__init__.py
rlgym_tools/extra_state_setters/augment_setter.py
rlgym_tools/extra_state_setters/construct_gamestates.py
rlgym_tools/extra_state_setters/goalie_state.py
