Metadata-Version: 2.1
Name: EARL-pytorch
Version: 0.5.2
Summary: EARL - Extensible Attention-based Rocket League model
Home-page: https://github.com/Rolv-Arild/EARL-pytorch
Author: Rolv-Arild Braaten
Author-email: rolv_arild@hotmail.com
License: MIT License
Platform: UNKNOWN
Classifier: Programming Language :: Python :: 3.7
Classifier: License :: OSI Approved :: MIT License
Classifier: Operating System :: OS Independent
